README
setup.py
django_insertblocks.egg-info/PKG-INFO
django_insertblocks.egg-info/SOURCES.txt
django_insertblocks.egg-info/dependency_links.txt
django_insertblocks.egg-info/not-zip-safe
django_insertblocks.egg-info/top_level.txt
insertblocks/__init__.py
insertblocks/models.py
insertblocks/templatetags/__init__.py
insertblocks/templatetags/insertblocks.py