Metadata-Version: 1.0
Name: django-insertblocks
Version: 0.1.0
Summary: Django Insert Blocks
Home-page: http://github.com/ojii/django-insertblocks
Author: Jonas Obrist
Author-email: jonas.obrist@divio.ch
License: UNKNOWN
Platform: UNKNOWN
